{
    "id": 3001637621,
    "node_id": "MDE5OkhlYWRSZWZEZWxldGVkRXZlbnQzMDAxNjM3NjIx",
    "url": "https://api.github.com/repos/ethereumclassic/ECIPs/issues/events/3001637621",
    "actor": {
      "login": "soc1c",
      "id": 47772477,
      "node_id": "MDQ6VXNlcjQ3NzcyNDc3",
      "avatar_url": "https://avatars.githubusercontent.com/u/47772477?v=4",
      "gravatar_id": "",
      "url": "https://api.github.com/users/soc1c",
      "html_url": "https://github.com/soc1c",
      "followers_url": "https://api.github.com/users/soc1c/followers",
      "following_url": "https://api.github.com/users/soc1c/following{/other_user}",
      "gists_url": "https://api.github.com/users/soc1c/gists{/gist_id}",
      "starred_url": "https://api.github.com/users/soc1c/starred{/owner}{/repo}",
      "subscriptions_url": "https://api.github.com/users/soc1c/subscriptions",
      "organizations_url": "https://api.github.com/users/soc1c/orgs",
      "repos_url": "https://api.github.com/users/soc1c/repos",
      "events_url": "https://api.github.com/users/soc1c/events{/privacy}",
      "received_events_url": "https://api.github.com/users/soc1c/received_events",
      "type": "User",
      "site_admin": false
    },
    "event": "head_ref_deleted",
    "commit_id": null,
    "commit_url": null,
    "created_at": "2020-02-03T10:34:24Z",
    "issue": {
      "url": "https://api.github.com/repos/ethereumclassic/ECIPs/issues/9",
      "repository_url": "https://api.github.com/repos/ethereumclassic/ECIPs",
      "labels_url": "https://api.github.com/repos/ethereumclassic/ECIPs/issues/9/labels{/name}",
      "comments_url": "https://api.github.com/repos/ethereumclassic/ECIPs/issues/9/comments",
      "events_url": "https://api.github.com/repos/ethereumclassic/ECIPs/issues/9/events",
      "html_url": "https://github.com/ethereumclassic/ECIPs/pull/9",
      "id": 398615017,
      "node_id": "MDExOlB1bGxSZXF1ZXN0MjQ0MjU2NDAw",
      "number": 9,
      "title": "krykoder sucks big push",
      "user": {
        "login": "realcodywburns",
        "id": 13103499,
        "node_id": "MDQ6VXNlcjEzMTAzNDk5",
        "avatar_url": "https://avatars.githubusercontent.com/u/13103499?v=4",
        "gravatar_id": "",
        "url": "https://api.github.com/users/realcodywburns",
        "html_url": "https://github.com/realcodywburns",
        "followers_url": "https://api.github.com/users/realcodywburns/followers",
        "following_url": "https://api.github.com/users/realcodywburns/following{/other_user}",
        "gists_url": "https://api.github.com/users/realcodywburns/gists{/gist_id}",
        "starred_url": "https://api.github.com/users/realcodywburns/starred{/owner}{/repo}",
        "subscriptions_url": "https://api.github.com/users/realcodywburns/subscriptions",
        "organizations_url": "https://api.github.com/users/realcodywburns/orgs",
        "repos_url": "https://api.github.com/users/realcodywburns/repos",
        "events_url": "https://api.github.com/users/realcodywburns/events{/privacy}",
        "received_events_url": "https://api.github.com/users/realcodywburns/received_events",
        "type": "User",
        "site_admin": false
      },
      "labels": [

      ],
      "state": "closed",
      "locked": false,
      "assignee": null,
      "assignees": [

      ],
      "milestone": null,
      "comments": 0,
      "created_at": "2019-01-13T03:23:20Z",
      "updated_at": "2020-02-03T10:34:24Z",
      "closed_at": "2019-01-13T17:44:21Z",
      "author_association": "MEMBER",
      "active_lock_reason": null,
      "pull_request": {
        "url": "https://api.github.com/repos/ethereumclassic/ECIPs/pulls/9",
        "html_url": "https://github.com/ethereumclassic/ECIPs/pull/9",
        "diff_url": "https://github.com/ethereumclassic/ECIPs/pull/9.diff",
        "patch_url": "https://github.com/ethereumclassic/ECIPs/pull/9.patch"
      },
      "body": "This completes issue #3 ",
      "performed_via_github_app": null
    },
    "performed_via_github_app": null
  }