{
    "id": 335599503,
    "node_id": "MDE3OlB1bGxSZXF1ZXN0UmV2aWV3MzM1NTk5NTAz",
    "user": {
      "login": "sorpaas",
      "id": 6277322,
      "node_id": "MDQ6VXNlcjYyNzczMjI=",
      "avatar_url": "https://avatars3.githubusercontent.com/u/6277322?v=4",
      "gravatar_id": "",
      "url": "https://api.github.com/users/sorpaas",
      "html_url": "https://github.com/sorpaas",
      "followers_url": "https://api.github.com/users/sorpaas/followers",
      "following_url": "https://api.github.com/users/sorpaas/following{/other_user}",
      "gists_url": "https://api.github.com/users/sorpaas/gists{/gist_id}",
      "starred_url": "https://api.github.com/users/sorpaas/starred{/owner}{/repo}",
      "subscriptions_url": "https://api.github.com/users/sorpaas/subscriptions",
      "organizations_url": "https://api.github.com/users/sorpaas/orgs",
      "repos_url": "https://api.github.com/users/sorpaas/repos",
      "events_url": "https://api.github.com/users/sorpaas/events{/privacy}",
      "received_events_url": "https://api.github.com/users/sorpaas/received_events",
      "type": "User",
      "site_admin": false
    },
    "body": "",
    "state": "APPROVED",
    "html_url": "https://github.com/ethereumclassic/ECIPs/pull/251#pullrequestreview-335599503",
    "pull_request_url": "https://api.github.com/repos/ethereumclassic/ECIPs/pulls/251",
    "author_association": "CONTRIBUTOR",
    "_links": {
      "html": {
        "href": "https://github.com/ethereumclassic/ECIPs/pull/251#pullrequestreview-335599503"
      },
      "pull_request": {
        "href": "https://api.github.com/repos/ethereumclassic/ECIPs/pulls/251"
      }
    },
    "submitted_at": "2019-12-21T10:30:39Z",
    "commit_id": "3640e96acc4a5b5756c4f028b430ad5e16fd86ef"
  }