{
    "id": 3142753895,
    "node_id": "MDE1OlJlZmVyZW5jZWRFdmVudDMxNDI3NTM4OTU=",
    "url": "https://api.github.com/repos/ethereumclassic/ECIPs/issues/events/3142753895",
    "actor": {
      "login": "TokenHash",
      "id": 29529586,
      "node_id": "MDQ6VXNlcjI5NTI5NTg2",
      "avatar_url": "https://avatars1.githubusercontent.com/u/29529586?v=4",
      "gravatar_id": "",
      "url": "https://api.github.com/users/TokenHash",
      "html_url": "https://github.com/TokenHash",
      "followers_url": "https://api.github.com/users/TokenHash/followers",
      "following_url": "https://api.github.com/users/TokenHash/following{/other_user}",
      "gists_url": "https://api.github.com/users/TokenHash/gists{/gist_id}",
      "starred_url": "https://api.github.com/users/TokenHash/starred{/owner}{/repo}",
      "subscriptions_url": "https://api.github.com/users/TokenHash/subscriptions",
      "organizations_url": "https://api.github.com/users/TokenHash/orgs",
      "repos_url": "https://api.github.com/users/TokenHash/repos",
      "events_url": "https://api.github.com/users/TokenHash/events{/privacy}",
      "received_events_url": "https://api.github.com/users/TokenHash/received_events",
      "type": "User",
      "site_admin": false
    },
    "event": "referenced",
    "commit_id": "7c0a9cc6c4cca182aa4b0c971fb0f78a33c799a6",
    "commit_url": "https://api.github.com/repos/TokenHash/ECIPs/commits/7c0a9cc6c4cca182aa4b0c971fb0f78a33c799a6",
    "created_at": "2020-03-18T18:52:12Z"
  }