{
    "url": "https://api.github.com/repos/ethereumclassic/ECIPs/issues/comments/587982520",
    "html_url": "https://github.com/ethereumclassic/ECIPs/issues/262#issuecomment-587982520",
    "issue_url": "https://api.github.com/repos/ethereumclassic/ECIPs/issues/262",
    "id": 587982520,
    "node_id": "MDEyOklzc3VlQ29tbWVudDU4Nzk4MjUyMA==",
    "user": {
      "login": "realcodywburns",
      "id": 13103499,
      "node_id": "MDQ6VXNlcjEzMTAzNDk5",
      "avatar_url": "https://avatars1.githubusercontent.com/u/13103499?v=4",
      "gravatar_id": "",
      "url": "https://api.github.com/users/realcodywburns",
      "html_url": "https://github.com/realcodywburns",
      "followers_url": "https://api.github.com/users/realcodywburns/followers",
      "following_url": "https://api.github.com/users/realcodywburns/following{/other_user}",
      "gists_url": "https://api.github.com/users/realcodywburns/gists{/gist_id}",
      "starred_url": "https://api.github.com/users/realcodywburns/starred{/owner}{/repo}",
      "subscriptions_url": "https://api.github.com/users/realcodywburns/subscriptions",
      "organizations_url": "https://api.github.com/users/realcodywburns/orgs",
      "repos_url": "https://api.github.com/users/realcodywburns/repos",
      "events_url": "https://api.github.com/users/realcodywburns/events{/privacy}",
      "received_events_url": "https://api.github.com/users/realcodywburns/received_events",
      "type": "User",
      "site_admin": false
    },
    "created_at": "2020-02-19T01:04:56Z",
    "updated_at": "2020-02-19T01:08:29Z",
    "author_association": "MEMBER",
    "body": "My Tldr of above is we have ill defined, at least imho, whom the testnet is designed to test for. If it is for mainet hf deployment testing, reset it. If it is a platform for app developers to run production parallel,  revert the bad fork, then implement as you would on mainnet. \r\n\r\n For me, I care more about publicly proving that hard fork features are non breaking than supporting an app graveyard",
    "reactions": {
      "url": "https://api.github.com/repos/ethereumclassic/ECIPs/issues/comments/587982520/reactions",
      "total_count": 0,
      "+1": 0,
      "-1": 0,
      "laugh": 0,
      "hooray": 0,
      "confused": 0,
      "heart": 0,
      "rocket": 0,
      "eyes": 0
    }
  }