{
    "url": "https://api.github.com/repos/ethereumclassic/ECIPs/issues/comments/676387695",
    "html_url": "https://github.com/ethereumclassic/ECIPs/issues/327#issuecomment-676387695",
    "issue_url": "https://api.github.com/repos/ethereumclassic/ECIPs/issues/327",
    "id": 676387695,
    "node_id": "MDEyOklzc3VlQ29tbWVudDY3NjM4NzY5NQ==",
    "user": {
      "login": "chrisfranko",
      "id": 3543217,
      "node_id": "MDQ6VXNlcjM1NDMyMTc=",
      "avatar_url": "https://avatars1.githubusercontent.com/u/3543217?v=4",
      "gravatar_id": "",
      "url": "https://api.github.com/users/chrisfranko",
      "html_url": "https://github.com/chrisfranko",
      "followers_url": "https://api.github.com/users/chrisfranko/followers",
      "following_url": "https://api.github.com/users/chrisfranko/following{/other_user}",
      "gists_url": "https://api.github.com/users/chrisfranko/gists{/gist_id}",
      "starred_url": "https://api.github.com/users/chrisfranko/starred{/owner}{/repo}",
      "subscriptions_url": "https://api.github.com/users/chrisfranko/subscriptions",
      "organizations_url": "https://api.github.com/users/chrisfranko/orgs",
      "repos_url": "https://api.github.com/users/chrisfranko/repos",
      "events_url": "https://api.github.com/users/chrisfranko/events{/privacy}",
      "received_events_url": "https://api.github.com/users/chrisfranko/received_events",
      "type": "User",
      "site_admin": false
    },
    "created_at": "2020-08-19T13:48:09Z",
    "updated_at": "2020-08-19T13:48:09Z",
    "author_association": "NONE",
    "body": "An \"eclipse attack\" is just a sybil attack with a fancier name.\n\nWhat does ideological beef mean? EXP launched before ETH Classic became a\nthing and there are plenty of people that hate EXP just for existing. We\nhave had people that try to disrupt the network just because of past\nmembers of our dev team.. ie me.. james clayton and others. Ideological\nbeef is basically an alias for EXP. And so far finality, although not a\nmagic bullet, has helped us stem off of those attacks because at the end of\nthe day, if they can only reorg 60 blocks at a time, the economy is never\nreceiving a shock. At most tx's would be delayed, not double spent. Delayed\ntxs are an inconvenience, double spends are catastrophic. We can deal with\ninconvenience, but catastrophe is costly. Finality adds peace of mind to\neconomy participants.\n\nOn Wed, 19 Aug 2020 at 06:07, Chris Hitchcott <notifications@github.com>\nwrote:\n\n> I wanted to raise another potential issue with the PirlGuard appraoch, and\n> open up discusson on how the network would handle eclipse attacks.\n>\n> Some background on eclipse attacks here:\n> https://www.youtube.com/watch?v=ss6VmIxGrBk\n>\n> As far as I understand, with PirlGuard, an eclipse attack (or an eclipse\n> attack + 40% attack) would do extra damage to the network compared to not\n> having PirlGuard in place.\n>\n> My impression is that the subjective finality that is added with PirlGuard\n> would, in the case of a long network partition (either by natural disasters\n> or an eclipse attack), permenantly splitting or fragmenting the network\n> (because of the reorg cap).\n>\n> This type of attack wouldn't be about trying to profit from a double\n> spend, but instead trying to create havok, perhaps in the hopes of\n> manipulating the price of ETC with leveraged short positions, or simply for\n> ideological reasons without a profit motive. For this reason I dont think\n> that the chains already use PirlGuard (with smaller market caps and less\n> ideological beef) prove that this kind of attack isn't plausable.\n>\n> —\n> You are receiving this because you were mentioned.\n> Reply to this email directly, view it on GitHub\n> <https://github.com/ethereumclassic/ECIPs/issues/327#issuecomment-676076211>,\n> or unsubscribe\n> <https://github.com/notifications/unsubscribe-auth/AA3BBMLCQBOJBNJKALM4UQDSBOP6JANCNFSM4PX2KMMA>\n> .\n>\n",
    "reactions": {
      "url": "https://api.github.com/repos/ethereumclassic/ECIPs/issues/comments/676387695/reactions",
      "total_count": 0,
      "+1": 0,
      "-1": 0,
      "laugh": 0,
      "hooray": 0,
      "confused": 0,
      "heart": 0,
      "rocket": 0,
      "eyes": 0
    },
    "performed_via_github_app": null
  }