{
    "url": "https://api.github.com/repos/ethereumclassic/ECIPs/issues/comments/676592669",
    "html_url": "https://github.com/ethereumclassic/ECIPs/issues/327#issuecomment-676592669",
    "issue_url": "https://api.github.com/repos/ethereumclassic/ECIPs/issues/327",
    "id": 676592669,
    "node_id": "MDEyOklzc3VlQ29tbWVudDY3NjU5MjY2OQ==",
    "user": {
      "login": "padenmoss",
      "id": 58626800,
      "node_id": "MDQ6VXNlcjU4NjI2ODAw",
      "avatar_url": "https://avatars0.githubusercontent.com/u/58626800?v=4",
      "gravatar_id": "",
      "url": "https://api.github.com/users/padenmoss",
      "html_url": "https://github.com/padenmoss",
      "followers_url": "https://api.github.com/users/padenmoss/followers",
      "following_url": "https://api.github.com/users/padenmoss/following{/other_user}",
      "gists_url": "https://api.github.com/users/padenmoss/gists{/gist_id}",
      "starred_url": "https://api.github.com/users/padenmoss/starred{/owner}{/repo}",
      "subscriptions_url": "https://api.github.com/users/padenmoss/subscriptions",
      "organizations_url": "https://api.github.com/users/padenmoss/orgs",
      "repos_url": "https://api.github.com/users/padenmoss/repos",
      "events_url": "https://api.github.com/users/padenmoss/events{/privacy}",
      "received_events_url": "https://api.github.com/users/padenmoss/received_events",
      "type": "User",
      "site_admin": false
    },
    "created_at": "2020-08-19T18:36:28Z",
    "updated_at": "2020-08-19T18:36:28Z",
    "author_association": "NONE",
    "body": "In light of the explanations of countermeasures by Dexaran against the eclipse attack and the network split attack, I support the implementation of PirlGuard.",
    "reactions": {
      "url": "https://api.github.com/repos/ethereumclassic/ECIPs/issues/comments/676592669/reactions",
      "total_count": 0,
      "+1": 0,
      "-1": 0,
      "laugh": 0,
      "hooray": 0,
      "confused": 0,
      "heart": 0,
      "rocket": 0,
      "eyes": 0
    },
    "performed_via_github_app": null
  }