{
    "url": "https://api.github.com/repos/ethereumclassic/ECIPs/issues/comments/677586856",
    "html_url": "https://github.com/ethereumclassic/ECIPs/issues/333#issuecomment-677586856",
    "issue_url": "https://api.github.com/repos/ethereumclassic/ECIPs/issues/333",
    "id": 677586856,
    "node_id": "MDEyOklzc3VlQ29tbWVudDY3NzU4Njg1Ng==",
    "user": {
      "login": "developerkevin",
      "id": 29807183,
      "node_id": "MDQ6VXNlcjI5ODA3MTgz",
      "avatar_url": "https://avatars2.githubusercontent.com/u/29807183?v=4",
      "gravatar_id": "",
      "url": "https://api.github.com/users/developerkevin",
      "html_url": "https://github.com/developerkevin",
      "followers_url": "https://api.github.com/users/developerkevin/followers",
      "following_url": "https://api.github.com/users/developerkevin/following{/other_user}",
      "gists_url": "https://api.github.com/users/developerkevin/gists{/gist_id}",
      "starred_url": "https://api.github.com/users/developerkevin/starred{/owner}{/repo}",
      "subscriptions_url": "https://api.github.com/users/developerkevin/subscriptions",
      "organizations_url": "https://api.github.com/users/developerkevin/orgs",
      "repos_url": "https://api.github.com/users/developerkevin/repos",
      "events_url": "https://api.github.com/users/developerkevin/events{/privacy}",
      "received_events_url": "https://api.github.com/users/developerkevin/received_events",
      "type": "User",
      "site_admin": false
    },
    "created_at": "2020-08-20T11:49:05Z",
    "updated_at": "2020-08-20T11:49:05Z",
    "author_association": "MEMBER",
    "body": "@q9f is there going to be room at the end for IOHK to demonstrate their checkpointing? I think we'll be able to fit it in towards the end?\r\n",
    "reactions": {
      "url": "https://api.github.com/repos/ethereumclassic/ECIPs/issues/comments/677586856/reactions",
      "total_count": 0,
      "+1": 0,
      "-1": 0,
      "laugh": 0,
      "hooray": 0,
      "confused": 0,
      "heart": 0,
      "rocket": 0,
      "eyes": 0
    },
    "performed_via_github_app": null
  }