{
    "url": "https://api.github.com/repos/ethereumclassic/ECIPs/issues/333",
    "repository_url": "https://api.github.com/repos/ethereumclassic/ECIPs",
    "labels_url": "https://api.github.com/repos/ethereumclassic/ECIPs/issues/333/labels{/name}",
    "comments_url": "https://api.github.com/repos/ethereumclassic/ECIPs/issues/333/comments",
    "events_url": "https://api.github.com/repos/ethereumclassic/ECIPs/issues/333/events",
    "html_url": "https://github.com/ethereumclassic/ECIPs/issues/333",
    "id": 677637913,
    "node_id": "MDU6SXNzdWU2Nzc2Mzc5MTM=",
    "number": 333,
    "title": "ETC Core Devs Call(s) 2020 Q3: Hardfork",
    "user": {
      "login": "q9f",
      "id": 58883403,
      "node_id": "MDQ6VXNlcjU4ODgzNDAz",
      "avatar_url": "https://avatars1.githubusercontent.com/u/58883403?v=4",
      "gravatar_id": "",
      "url": "https://api.github.com/users/q9f",
      "html_url": "https://github.com/q9f",
      "followers_url": "https://api.github.com/users/q9f/followers",
      "following_url": "https://api.github.com/users/q9f/following{/other_user}",
      "gists_url": "https://api.github.com/users/q9f/gists{/gist_id}",
      "starred_url": "https://api.github.com/users/q9f/starred{/owner}{/repo}",
      "subscriptions_url": "https://api.github.com/users/q9f/subscriptions",
      "organizations_url": "https://api.github.com/users/q9f/orgs",
      "repos_url": "https://api.github.com/users/q9f/repos",
      "events_url": "https://api.github.com/users/q9f/events{/privacy}",
      "received_events_url": "https://api.github.com/users/q9f/received_events",
      "type": "User",
      "site_admin": false
    },
    "labels": [
      {
        "id": 1658195407,
        "node_id": "MDU6TGFiZWwxNjU4MTk1NDA3",
        "url": "https://api.github.com/repos/ethereumclassic/ECIPs/labels/status:%200%20wip",
        "name": "status: 0 wip",
        "color": "f0f0f0",
        "default": false,
        "description": "ECIP is still work in progress and shall not be merged."
      },
      {
        "id": 1154785129,
        "node_id": "MDU6TGFiZWwxMTU0Nzg1MTI5",
        "url": "https://api.github.com/repos/ethereumclassic/ECIPs/labels/type:%20meta",
        "name": "type: meta",
        "color": "cfd3d7",
        "default": false,
        "description": "ECIPs of type \"Meta\" - bundling proposals for upgrades."
      }
    ],
    "state": "open",
    "locked": false,
    "assignee": null,
    "assignees": [

    ],
    "milestone": null,
    "comments": 24,
    "created_at": "2020-08-12T12:07:28Z",
    "updated_at": "2020-08-22T18:16:02Z",
    "closed_at": null,
    "author_association": "MEMBER",
    "active_lock_reason": null,
    "body": "Ref https://doodle.com/poll/yutswfi8ngdts87b\r\n\r\nRef https://medium.com/ethereum-classic-labs/etc-network-security-plan-fed70402b727\r\n\r\n# ETC Core Devs Call(s) 2020 Q3: Hardfork\r\n* When: _Thursday, August 20, 2020, 12pm UTC, 60 minutes max -- proposal gathering and discussion only_\r\n* When: **Friday, August 28, 2020, 4pm UTC,** 60 minutes max -- proposal evaluation and **consensus finding**\r\n* Where: Ethereum Classic Discord https://discord.gg/dwxb6nf #ecips channel. Will use/create a voice channel ad hoc.\r\n\r\n## Agenda 08/28 \"Focus session\"\r\n- Teams Check-in\r\n- Focus: ECIP-1049 \"Keccak256\"\r\n- Focus: Checkpointing & Timestamping\r\n- Focus: VeriBlock and if time permitting, PirlGuard\r\n\r\n## Agenda 08/20 \"Overview session\"\r\n- Teams Check-in\r\n  - Byzantine Fault\r\n  - ChainSafe Systems\r\n  - ETC Core (& ETC Labs)\r\n  - ETC Cooperative\r\n  - Input Output HK (IOHK)\r\n- Mining Algorithm Change\r\n  - ECIP 1049 \"Keccak256\"\r\n  - ECIP 1093 \"RandomX\"\r\n  - (_time permitting_) ECBP 1076 \"Miner Signaling\"\r\n- Other Proposals addressing PoW Security\r\n  - ECIP 1092 \"Pirlguard\"\r\n  - ECIP 1094 \"VeriBlock\"\r\n  - (_unpublished_) \"Checkpointing and Timestamping\"\r\n- (_time permitting_) Ethereum Berlin Hardfork\r\n  - (_time permitting_) EIP-2315: Simple Subroutines for the EVM\r\n  - (_time permitting_) EIP-2537: BLS12-381 curve operations\r\n  - (_time permitting_) EIP-2046: Reduced gas cost for static calls made to precompiles\r\n  - (_time permitting_) EIP-2565: Repricing of the EIP-198 ModExp precompile\r\n- (_time permitting_) Other topics that have to be addressed urgently.\r\n  - (_time permitting_) Gas Range Discussion: Upper and Lower Bounds\r\n  - (_time permitting_) Gas limit, backwards compatibility, slower blocks\r\n\r\nPlease post all relevant proposals below that should be discussed and evaludated.",
    "reactions": {
      "url": "https://api.github.com/repos/ethereumclassic/ECIPs/issues/333/reactions",
      "total_count": 3,
      "+1": 3,
      "-1": 0,
      "laugh": 0,
      "hooray": 0,
      "confused": 0,
      "heart": 0,
      "rocket": 0,
      "eyes": 0
    },
    "performed_via_github_app": null
  }