{
    "url": "https://api.github.com/repos/ethereumclassic/ECIPs/issues/comments/685303577",
    "html_url": "https://github.com/ethereumclassic/ECIPs/issues/342#issuecomment-685303577",
    "issue_url": "https://api.github.com/repos/ethereumclassic/ECIPs/issues/342",
    "id": 685303577,
    "node_id": "MDEyOklzc3VlQ29tbWVudDY4NTMwMzU3Nw==",
    "user": {
      "login": "ponchoetc",
      "id": 70486112,
      "node_id": "MDQ6VXNlcjcwNDg2MTEy",
      "avatar_url": "https://avatars3.githubusercontent.com/u/70486112?v=4",
      "gravatar_id": "",
      "url": "https://api.github.com/users/ponchoetc",
      "html_url": "https://github.com/ponchoetc",
      "followers_url": "https://api.github.com/users/ponchoetc/followers",
      "following_url": "https://api.github.com/users/ponchoetc/following{/other_user}",
      "gists_url": "https://api.github.com/users/ponchoetc/gists{/gist_id}",
      "starred_url": "https://api.github.com/users/ponchoetc/starred{/owner}{/repo}",
      "subscriptions_url": "https://api.github.com/users/ponchoetc/subscriptions",
      "organizations_url": "https://api.github.com/users/ponchoetc/orgs",
      "repos_url": "https://api.github.com/users/ponchoetc/repos",
      "events_url": "https://api.github.com/users/ponchoetc/events{/privacy}",
      "received_events_url": "https://api.github.com/users/ponchoetc/received_events",
      "type": "User",
      "site_admin": false
    },
    "created_at": "2020-09-02T05:14:25Z",
    "updated_at": "2020-09-02T05:14:25Z",
    "author_association": "NONE",
    "body": "Centralization of hashrate is the worst thing ETC need to do, its needed software improvements.. not only changing algo en pray god all the issues gone, if you change ethash algo you willl kill the potential grown of ETC With all ETH Miners that will migrate into ETC When eth 2.0 arrives\r\n\r\nI dont know why ETC Dev are forced to trying in every way kill ethereum classic\r\nthey want to split community into these words we as a important part of ethereum classic we don't accept sha3 we don't accept centralization of ETC\r\nthat does not represent what ETC Is\r\n\r\nand if you ETC DEV you continue with this ridiculous statment about sha3 you can see... that any miner will head with you..\r\nand you will lose the strongest part of a Proof of work ecosystem\r\nplease regreet this actions and Improve into real solutions dont make ETC Centralized.",
    "reactions": {
      "url": "https://api.github.com/repos/ethereumclassic/ECIPs/issues/comments/685303577/reactions",
      "total_count": 0,
      "+1": 0,
      "-1": 0,
      "laugh": 0,
      "hooray": 0,
      "confused": 0,
      "heart": 0,
      "rocket": 0,
      "eyes": 0
    },
    "performed_via_github_app": null
  }