{
    "url": "https://api.github.com/repos/ethereumclassic/ECIPs/issues/comments/742453995",
    "html_url": "https://github.com/ethereumclassic/ECIPs/issues/401#issuecomment-742453995",
    "issue_url": "https://api.github.com/repos/ethereumclassic/ECIPs/issues/401",
    "id": 742453995,
    "node_id": "MDEyOklzc3VlQ29tbWVudDc0MjQ1Mzk5NQ==",
    "user": {
      "login": "faraggi",
      "id": 264382,
      "node_id": "MDQ6VXNlcjI2NDM4Mg==",
      "avatar_url": "https://avatars2.githubusercontent.com/u/264382?v=4",
      "gravatar_id": "",
      "url": "https://api.github.com/users/faraggi",
      "html_url": "https://github.com/faraggi",
      "followers_url": "https://api.github.com/users/faraggi/followers",
      "following_url": "https://api.github.com/users/faraggi/following{/other_user}",
      "gists_url": "https://api.github.com/users/faraggi/gists{/gist_id}",
      "starred_url": "https://api.github.com/users/faraggi/starred{/owner}{/repo}",
      "subscriptions_url": "https://api.github.com/users/faraggi/subscriptions",
      "organizations_url": "https://api.github.com/users/faraggi/orgs",
      "repos_url": "https://api.github.com/users/faraggi/repos",
      "events_url": "https://api.github.com/users/faraggi/events{/privacy}",
      "received_events_url": "https://api.github.com/users/faraggi/received_events",
      "type": "User",
      "site_admin": false
    },
    "created_at": "2020-12-10T11:11:11Z",
    "updated_at": "2020-12-10T11:11:11Z",
    "author_association": "NONE",
    "body": "I accept the _nomination_. \r\nCurrent editors can make the decision on timing for my acceptance/denial.\r\n\r\n@q9f  For clarification, I will be representing IOHK and not Pegasys.",
    "reactions": {
      "url": "https://api.github.com/repos/ethereumclassic/ECIPs/issues/comments/742453995/reactions",
      "total_count": 0,
      "+1": 0,
      "-1": 0,
      "laugh": 0,
      "hooray": 0,
      "confused": 0,
      "heart": 0,
      "rocket": 0,
      "eyes": 0
    },
    "performed_via_github_app": null
  }